argus_uav/__init__.py
argus_uav/cli.py
argus_uav/cli_main.py
argus_uav/attacks/__init__.py
argus_uav/attacks/coordinated.py
argus_uav/attacks/phantom_uav.py
argus_uav/attacks/position_spoof.py
argus_uav/consensus/__init__.py
argus_uav/consensus/average_consensus.py
argus_uav/core/__init__.py
argus_uav/core/remote_id.py
argus_uav/core/swarm.py
argus_uav/core/uav.py
argus_uav/crypto/__init__.py
argus_uav/crypto/ed25519_signer.py
argus_uav/detection/__init__.py
argus_uav/detection/centrality.py
argus_uav/detection/crypto_detector.py
argus_uav/detection/ml_detection.py
argus_uav/detection/spectral.py
argus_uav/detection/temporal_correlation.py
argus_uav/evaluation/__init__.py
argus_uav/evaluation/live_visualization.py
argus_uav/evaluation/metrics.py
argus_uav/evaluation/visualizations.py
argus_uav/experiments/__init__.py
argus_uav/experiments/config_schema.py
argus_uav/experiments/runner.py
argus_uav/utils/__init__.py
argus_uav/utils/logging_config.py
argus_uav/utils/random_seeds.py
argus_uav-0.2.0.dist-info/METADATA
argus_uav-0.2.0.dist-info/WHEEL
argus_uav-0.2.0.dist-info/entry_points.txt
argus_uav-0.2.0.dist-info/licenses/LICENSE
argus_uav-0.2.0.dist-info/RECORD
