Metadata-Version: 2.4
Name: argus_uav
Version: 0.2.0
Summary:  A UAV Remote ID Spoofing Defense System 
Project-URL: Homepage, https://github.com/Sang-Buster/Argus
Project-URL: Documentation, https://deepwiki.com/Sang-Buster/Argus
Project-URL: Repository, https://github.com/Sang-Buster/Argus
Author-email: Sang Buster <hello@singsongaftermath.com>
License: MIT License
License-File: LICENSE
Keywords: anomaly-detection,cryptography,cybersecurity,detection,drone,graph-theory,machine-learning,network-analysis,remote-id,security,spoofing,swarm,uav
Classifier: Development Status :: 4 - Beta
Classifier: Environment :: Console
Classifier: Intended Audience :: Education
Classifier: Intended Audience :: Science/Research
Classifier: License :: OSI Approved :: MIT License
Classifier: Operating System :: OS Independent
Classifier: Programming Language :: Python :: 3.10
Classifier: Programming Language :: Python :: 3.11
Classifier: Programming Language :: Python :: 3.12
Classifier: Topic :: Scientific/Engineering :: Artificial Intelligence
Classifier: Topic :: Security
Classifier: Topic :: System :: Networking
Requires-Python: >=3.10
Requires-Dist: matplotlib>=3.10.7
Requires-Dist: networkx>=3.4.2
Requires-Dist: numpy>=2.2.6
Requires-Dist: pycryptodome>=3.23.0
Requires-Dist: pyside6>=6.7.0
Requires-Dist: scikit-learn>=1.7.2
